LICENSE
MANIFEST.in
README.md
setup.py
sfsutils/__init__.py
sfsutils/_sfsutils.py
sfsutils/_sfsutils.pyx
sfsutils.egg-info/PKG-INFO
sfsutils.egg-info/SOURCES.txt
sfsutils.egg-info/dependency_links.txt
sfsutils.egg-info/not-zip-safe
sfsutils.egg-info/top_level.txt