Metadata-Version: 2.1
Name: sfsutils
Version: 1.1.1
Summary: A KSP SFS savefile parser
Home-page: https://github.com/mark9064/sfsutils
Author: mark9064
Classifier: Programming Language :: Python :: 3
Classifier: Programming Language :: Cython
Classifier: License :: OSI Approved :: GNU General Public License v3 (GPLv3)
Classifier: Operating System :: OS Independent
Classifier: Development Status :: 4 - Beta
Classifier: Natural Language :: English
Requires-Python: >=3.7
License-File: LICENSE
